paint.py
raffaello.py
presets/__init__.py
presets/at
presets/cmake
presets/cpp
presets/cppcheck
presets/dmesg
presets/errors
presets/gpsd
presets/modemmanager
presets/nmea
presets/syslog
raffaello-4.0.0.dist-info/LICENCE.txt
raffaello-4.0.0.dist-info/METADATA
raffaello-4.0.0.dist-info/WHEEL
raffaello-4.0.0.dist-info/entry_points.txt
raffaello-4.0.0.dist-info/top_level.txt
raffaello-4.0.0.dist-info/RECORD
