Metadata-Version: 2.1
Name: raffaello
Version: 4.0.0
Summary: Raffaello command-line output colorizer
Home-page: https://github.com/clobrano/raffaello
Author: Carlo Lobrano
Author-email: c.lobrano@gmail.com
License: MIT
Keywords: formatter,console,colorizer
Platform: UNKNOWN
Classifier: Development Status :: 5 - Production/Stable
Classifier: Topic :: Utilities
Classifier: Topic :: System :: Logging
Requires-Dist: docopt
